autocommit/__init__.py
autocommit/git_helpers.py
autocommit/main.py
git_autocommit-0.1.0.dist-info/METADATA
git_autocommit-0.1.0.dist-info/WHEEL
git_autocommit-0.1.0.dist-info/entry_points.txt
git_autocommit-0.1.0.dist-info/top_level.txt
git_autocommit-0.1.0.dist-info/RECORD
