Metadata-Version: 2.1
Name: git-autocommit
Version: 0.1.0
Summary: A tool to automatically generate Git commit messages using local LLMs
Home-page: https://github.com/technoabsurdist/autocommit
Author: Emilio
Author-email: andere.emi@gmail.com
Classifier: Programming Language :: Python :: 3
Classifier: License :: OSI Approved :: MIT License
Classifier: Operating System :: OS Independent
Requires-Python: >=3.6
Requires-Dist: ollama
